{"packages":{"git.shin.3dtools":{"Name":"3DTools Cracked","Icon":"file:///Library/PreferenceBundles/3DTools.bundle/icon@2x.png","MD5sum":"5ecf5bc523016ce897d20ebb8605301f","Section":"Tweaks","Version":"1.0.5","birthtimeMs":1606367064367.3997},"git.shin.BigClock":{"Name":"BigClock Widget","MD5sum":"4675bd5d7de5c085897b500a927df87b","Section":"Widgets","Version":"1.0","birthtimeMs":1606367065447.3997},"git.shin.lpm":{"Name":"RealLPM Cracked","MD5sum":"64bec4a572b6638c297cec7fe0844d5d","Section":"Tweaks","Version":"1.1.3","birthtimeMs":1606367077727.3997},"me.lightmann.transparentnotif":{"Name":"TransparentNotif","Icon":"file:///Library/PreferenceBundles/TransparentNotifPrefs.bundle/icon@2x.png","MD5sum":"0cb627f0176b2e6f4206895b656b14d5","Section":"Tweaks","Version":"1.0.6.3-1","birthtimeMs":1606367079057.3997}},"lastUpdate":1606367079057.3997,"length":4}